{
  "title": "Would You Pay $6.2 Million for This Business? - NYTimes.com",
  "authors": [
    "Josh Patrick"
  ],
  "publish_date": "2013-01-30T00:00:00",
  "top_image": "https://static01.nyt.com/images/blogs_v5/../icons/t_logo_291_black.png",
  "keywords": [
    "owner",
    "training",
    "buyer",
    "62",
    "pay",
    "work",
    "business",
    "financial",
    "company",
    "industry",
    "look",
    "million"
  ],
  "summary": "",
  "url": "http://boss.blogs.nytimes.com/2013/01/30/would-you-pay-6-2-million-for-this-business/?src=rechp&gwh=F5AE5CEB6F6665460D7BBF64AA736A4F",
  "formatted_date": "2013-01-31 12:35:58"
}