{
  "title": "The Lonely Hearts Club man \u2013 BBC Science Focus",
  "authors": [],
  "publish_date": "2022-10-11T00:00:00",
  "top_image": "https://dj9jqhxgw9833.cloudfront.net/uploads/sites/42/2022/10/10639bd1-d31d-4778-af71-4f2a8aa3a708.jpg",
  "keywords": [
    "hearts",
    "club",
    "close",
    "man",
    "lonely",
    "boys",
    "likely",
    "science",
    "university",
    "men",
    "way",
    "friends",
    "bbc",
    "women",
    "focus",
    "social"
  ],
  "summary": "",
  "url": "https://c01.purpledshub.com/bbcsciencefocus/2022/10/11/the-lonely-hearts-club-man/",
  "formatted_date": "2022-10-22 22:15:40"
}