{
  "title": "Sam Hinkie (Ft. Abraham Lincoln, Amos Tversky, Jeff Bezos, Jeff Van Gundy, Max Planck, Tim Urban & Warren Buffett) \u2013 Philadelphia 76ers Resignation Letter",
  "authors": [],
  "publish_date": null,
  "top_image": "",
  "keywords": [
    "trigger",
    "submitting",
    "triggered",
    "page",
    "thisyou",
    "website",
    "word",
    "using",
    "security",
    "required",
    "attention",
    "sql"
  ],
  "summary": "",
  "url": "http://genius.com/Sam-hinkie-philadelphia-76ers-resignation-letter-annotated",
  "formatted_date": "2016-04-07 11:27:55"
}