{
  "title": "The college trap that keeps people poor",
  "authors": [
    "Story By"
  ],
  "publish_date": "2014-12-15T00:00:00",
  "top_image": "http://www.washingtonpost.com/sf/business/wp-content/uploads/sites/20/2014/11/ftl-3-fb-image.jpg",
  "keywords": [
    "lowincome",
    "\u00e2",
    "beat",
    "students",
    "away",
    "\u00e2she\u00e2s",
    "worth",
    "\u00e2do",
    "\u00e2i",
    "\u00e2no",
    "stone",
    "graduating",
    "working",
    "forces",
    "college"
  ],
  "summary": "",
  "url": "http://www.washingtonpost.com/sf/business/2014/12/15/the-college-trap-that-keeps-people-poor/",
  "formatted_date": "2014-12-16 21:11:37"
}