{
  "title": "When Is It OK to Be Alone With Another Person\u2019s Spouse?",
  "authors": [],
  "publish_date": null,
  "top_image": "https://web-static.archive.org/_static/images/archive.ico",
  "keywords": [
    "infoarchiveorg",
    "machine",
    "javascript",
    "questions",
    "wayback",
    "support",
    "requires",
    "browser",
    "email"
  ],
  "summary": "",
  "url": "http://www.slate.com/articles/double_x/doublex/2015/11/when_is_it_ok_to_be_alone_with_another_person_s_spouse.html",
  "formatted_date": "2015-11-11 18:51:08"
}