{
  "uid": "47a5728f7444cf74",
  "source": "/home/ubuntu/dev/atlas/inputs/Docs/Salesforce Acquires Mulesoft The Enterprise Cloud Opportunity Salesforces Opportunity Stratechery Daily Update2018322_032118.html",
  "title": "Salesforce Acquires Mulesoft The Enterprise Cloud Opportunity Salesforces Opportunity Stratechery Daily Update2018322_032118",
  "content_type": "document",
  "status": "success",
  "processed_at": "2025-08-23T20:46:10.266864",
  "file_size": 261292,
  "source_type": "local_html"
}