{
  "uid": "7f038a748a6bd9c5",
  "content_type": "article",
  "source": "http://thepointsguy.com/2015/07/guide-to-canceling-award-tickets/",
  "title": "Comprehensive Guide to Canceling Airline Award Tickets - The Points Guy",
  "status": "success",
  "date": "2025-08-13T18:50:23.311389",
  "error": null,
  "content_path": "output/articles/markdown/7f038a748a6bd9c5.md",
  "html_path": null,
  "audio_path": null,
  "transcript_path": null,
  "tags": [],
  "notes": [],
  "fetch_method": "wayback_machine",
  "fetch_details": {
    "attempts": [],
    "successful_method": "wayback_machine",
    "is_truncated": true,
    "total_attempts": 0,
    "fetch_time": null
  },
  "category_version": null,
  "last_tagged_at": null,
  "source_hash": null,
  "type_specific": {
    "category_version": null,
    "last_tagged_at": null,
    "source_hash": null,
    "summary_text": null,
    "extract_error": null
  },
  "created_at": "2025-08-13T18:50:30.339156",
  "updated_at": "2025-08-13T18:50:30.339158"
}