{
  "uid": "be753e3e5b8d0169",
  "content_type": "article",
  "source": "http://www.southsidesox.com/2014/7/15/5900595/10-minutes-with-frank-thomas-before-his-hall-of-fame-day",
  "title": "10 minutes with Frank Thomas before his Hall of Fame day | South Side Sox",
  "status": "success",
  "date": "2025-08-13T19:39:56.914206",
  "error": null,
  "content_path": "output/articles/markdown/be753e3e5b8d0169.md",
  "html_path": null,
  "audio_path": null,
  "transcript_path": null,
  "tags": [],
  "notes": [],
  "fetch_method": "direct",
  "fetch_details": {
    "attempts": [],
    "successful_method": "direct",
    "is_truncated": false,
    "total_attempts": 0,
    "fetch_time": null
  },
  "category_version": null,
  "last_tagged_at": null,
  "source_hash": null,
  "type_specific": {
    "category_version": null,
    "last_tagged_at": null,
    "source_hash": null,
    "summary_text": null,
    "extract_error": null
  },
  "created_at": "2025-08-13T19:40:01.277158",
  "updated_at": "2025-08-13T19:40:01.277160"
}