{
  "uid": "70b223ab22c2b27f",
  "source_file": "inputs/saved_html/Larry Ray and the Stolen Kids of SarahLawrence_021120_20250818_154459.html",
  "content_type": "document",
  "processing_status": "started",
  "processing_timestamp": "2025-08-19T09:28:03.836612",
  "file_size": 550467,
  "file_extension": ".html",
  "mime_type": "text/html",
  "created_at": "2025-08-19T09:19:08.871569",
  "modified_at": "2025-08-17T18:57:55.386671",
  "file_hash": "e3304e142094002e",
  "total_elements": 130,
  "element_types": {
    "Title": 1,
    "Text": 8,
    "NarrativeText": 121
  },
  "has_tables": false,
  "has_images": false,
  "estimated_reading_time": 46,
  "language": "eng",
  "structure_analysis": {
    "titles": 1,
    "narrative_texts": 121,
    "list_items": 0,
    "tables": 0
  },
  "word_count": 9264
}