{
  "uid": "8b8c42b168c23fff",
  "source_file": "inputs/saved_emails/=UTF-8qSotheby=E2=80=99s_=E2=80=9CTrump_Rally,=E2=80=9D_Arta=E2=80=99s=\r\n =UTF-8q_Explosion_&_An_E-Commerce_Mystery=_Wed,_29_Jan_2025_22-45-10_+0000_194b43d7a4fcdb49_20250818_154500.eml",
  "content_type": "document",
  "processing_status": "started",
  "processing_timestamp": "2025-08-19T09:39:11.909271",
  "file_size": 112256,
  "file_extension": ".eml",
  "mime_type": "message/rfc822",
  "created_at": "2025-08-19T09:23:34.746779",
  "modified_at": "2025-08-17T18:48:03.120225",
  "file_hash": "dd60f100ed2a744e",
  "total_elements": 3,
  "element_types": {
    "NarrativeText": 1,
    "Table": 1,
    "Image": 1
  },
  "has_tables": true,
  "has_images": false,
  "estimated_reading_time": 2,
  "language": "eng",
  "structure_analysis": {
    "titles": 0,
    "narrative_texts": 1,
    "list_items": 0,
    "tables": 1
  },
  "word_count": 578
}