{
  "uid": "cf0aade0f4d49c45",
  "source_file": "inputs/saved_emails/Shopify Earnings, Software Self-Awareness, Rebels and the Arms Dealer (Stratechery Update 11-13-2024)_Wed,_13_Nov_2024_11-12-28_+0000_1932539b0e62f039_20250818_154500.eml",
  "structured_content": [
    {
      "id": 0,
      "type": "NarrativeText",
      "text": "Shopify is back to sustained growth thanks to discovering the leverage of software."
    },
    {
      "id": 1,
      "type": "Table",
      "text": "View in browser Shopify Earnings, Software Self-Awareness, Rebels and the Arms Dealer Wednesday, November 13, 2024 Listen to this Update in your podcast player Good morning, On last week’s episode of Sharp China , Bill and Andrew reacted to Trump’s election and what it means for U.S.-China relations. On to the Update: Shopify Earnings From Bloomberg : Shopify Inc. soared after saying it will sustain rapid sales growth into the holiday shopping season, suggesting the Canadian e-commerce company’s strategy to lure larger businesses is paying off. Shopify said it expects percentage revenue growth for the current quarter ending in December to be in the mid to high twenties on a year-over-year basis. Analysts were looking for 23%. Shopify added 16 new enterprise clients in the third quarter, President Harley Finkelstein told investors on a Tuesday call. That helped boost revenue for the period by 26% to $2.16 billion, the company said in a statement Tuesday, beating the $2.12 billion average estimate of analysts surveyed by Bloomberg. In addition to attracting bigger customers, Shopify is benefiting from strength across Europe, more clients using its in-store payments tools and rapid growth in the business-to-business segment that’s attracting wholesale suppliers, Finkelstein said. “Shopify is not just for small businesses in North America,” he said. “We’re for every sized brand everywhere in the world.” Shopify is absolutely killing it. Finkelstein opened his prepared remarks with the numbers: As we say each quarter, Shopify is building for the long term. Our consistent results quarter after quarter confirm that our strategy is working incredibly well. Q3 was another amazing quarter across the board. GMV was up 24%, marking our fifth consecutive quarter where GMV growth was greater than 20%. Revenue was up 26%. Operating income more than doubled from last year. And free cash flow margin expanded to 19%. These are not just numbers. They reinforce that Shopify is an industry leader, delivering on both growth and margins, all while simultaneously creating and leaning into opportunities that bolster our growth. Finkelstein followed up with three things he wanted investors to remember: So, before we dive in, let me start by saying this. If you walk away from this call with anything, it should be these three things: One, entrepreneurship and commerce are growing, and Shopify is capturing an increasing share of this vast and expanding market. Two, Shopify is increasingly the go-to-platform of choice not just for entrepreneurship, but for all of commerce. We are well-positioned for extensive growth across different merchant segments, size, geographies, channels, and products. And three, as our merchants do better, Shopify does better. Our business model prioritizes merchant first, fueled by a high-velocity product innovation engine that makes the hard things easy and everything else possible. I would like to add a fourth thing; here is the chart of Shopify’s GMV over the last 10 years: The COVID boom is super obvious; what I think remains under-appreciated is the impact of ATT. I wrote in July 2022 after posting the above chart: You can clearly see the pandemic impact, but what is concerning is not simply that GMV growth returned to trend in late 2020, but, over the last two quarters, dropped below trend. That could be the pandemic hangover, it could be macroeconomic conditions, but it sure seems like the most obvious explanation is that it is the impact of ATT. It follows, then, that an under-appreciated reason for Shopify’s return to strength is Meta’s recovery from ATT: a lot of GMV is downstream from Meta ads in particular, and Meta’s return to growth is unsurprisingly correlated to Shopify’s return to growth as well. That noted, Shopify does deserve more credit than just riding Meta’s coattails; consistent growth rates above 20% is not a return to the pre-COVID trendline, but a clear acceleration to a new baseline, and here Finkelstein’s three things ring true, particularly point number two. Software Self-Awareness Finkelstein said in his closing statement: For those of you that have been following the Shopify story for quite some time, you know that we are a company that is laser-focused on our merchants. You’ve heard that we have a very long-term vision that we think could help them succeed. I think you will continue to see us seize opportunities and invest, as Jeff described, with discipline to further establish ourselves as the leader in commerce. And this has enabled us to deliver, as you can see from these results, some of the strongest results in the industry quarter after quarter. I also want to repeat, this is the best version of Shopify yet. We really like our size, our shape. We like how we’re operating. We really think it gives us the ability to grow the business and invest in the future. And so, I just wanted to finish with that point. And now for us, back to helping our merchants crush at this holiday season and well into the future. I don’t question Shopify’s laser-focus on merchants; what I would say, as someone who has been following the Shopify story for a long-time, is that it was precisely that focus that led Shopify astray a few years ago. To refresh your memory: That 2022 plummet in value wasn’t just the COVID overhang, and it wasn’t just ATT; it was also when Shopify decided to compete more directly with Amazon and get into the logistics business (beyond just being an asset-lite platform ). Finkelstein said on the February 2022 earnings call announcing the shift away from an asset-lite model: We are excited to update you today on what we’ve learned, how far we’ve come and especially on where we’re heading as we move out of the prototype phase and into the build phase. We are consolidating our network to larger facilities. We’ll operate more of them ourselves, and we’ll unify the warehouse management software that we’ve been building and testing over the past 18 months. We expect that these changes will enable us to deliver packages in 2 days or less to more than 90% of the U.S. population, while minimizing the inventory investment for SFN merchants. While Amy will go into more detail as to what our evolved vision looks like from a financial perspective, I can tell you, from a merchant’s perspective, Shopify Fulfillment can be life-changing for their businesses. We hear from merchants that fulfillment is only something you think about when it isn’t working well, and they are thrilled that they now never have to think about it. The stockouts and pre orders that took the shine off strong demand for the new releases, largely became, I think, in the past, with Shopify Fulfillment. And just recently, I heard from a merchant who tells me that he sleeps even better because Shopify Fulfillment just works. Comments like these fuel our ambition, and we’ll continue to explore opportunities to give merchants more visibility and control over their most important assets. That’s a lot of talk about merchants! It was also a disaster. Fast forward to May 2023 , and CEO Tobi Lütke announced layoffs and the end of Shopify’s logistics ambitions through the framework of “main quests” and “side quests”; logistics was the latter. Lütke claimed it was still worth it, but I’m not sure anyone agreed. Here’s the thing: logistics were and are a big challenge for merchants. It is a problem that needs to be solved. In this case, however, Shopify was too laser-focused on merchants; logistics was a situation where they needed to not just understand the problems being faced by their merchants, but also understand themselves and what problems they were actually capable of solving. Specifically, Shopify is a software company, and that puts one hard constraint on your business: you need to go horizontal, not vertical. Software requires huge amounts of R&D but it also scales infinitely; software businesses profit by maximizing leverage on their investments, which means serving more customers with the same capabilities. Logistics, though, means the physical world, which means variable costs and a limited addressable market; this limits the leverage you get from software, without decreasing the need for R&D. Rebels and the Arms Dealer That, then, takes me full circle to these results: what has shifted the curve for Shopify is not just shedding a logistics business that didn’t fit their nature, but in fact embracing their nature and working to expand their customer base. Note this (excellent) question and answer from yesterday’s earnings call: You guys have positioned Shopify as the rebels going up against the larger online marketplaces, but arguably the consolidation of e-commerce market share is occurring to a smaller number of platforms, including Shopify. And so, I wonder if your views of how the industry is evolving or changing, what that consolidation means for your merchant base, and ultimately, how that influences product plans for things like Shop App? Thank you. A couple of things are happening I think when it comes to larger brands and retailers. One is, all across the board, they’re looking for a unified commerce system. They’re not looking for standalone, single-channel products anymore. I’ve used this metaphor before of the browser and the browser tabs. And what we’re seeing is that these large companies, specifically complex ones that have high GMV, they want to collapse those tabs from eight to one. And this idea of having a modern future-proofed retail operating system that is unified across every channel like Shopify is very compelling. Secondly, historically, when it came to larger brands, our focus was really on Shopify Plus. We had sort of this one-size-fits-all for larger brands. But now we have an enterprise product, we have Shopify Plus, we have Commerce Components. And Commerce Components, in particular, is really compelling because it’ll — I mentioned this in my prepared remarks, but we’re now seeing brands that are calling us, and three weeks later, they now have Shop Pay installed on their checkout or brands, for example, like On Running, one of my favorite brands that has Shopify’s checkout as a Commerce Component that they’ve now taken. So, there are all these new sort of gateways into Shopify or on ramps to Shopify on the Enterprise side. There are two points here. First, Shopify has refocused its attention on delivering a solution to all aspect of a merchant’s software needs; this is what the company is capable of doing, and it increases both its value to merchants and also its attractiveness to larger companies. Secondly, Shopify has significantly increased both the segmentation of its products and their composability. Different capabilities are available at different price points and with different go-to-market approaches, but it all rests on a common R&D effort; similarly, companies can just use one or two of Shopify’s offerings, like the Shop Pay button, which both increases the leverage on that product and also provides a beachhead for selling more. In other words, while Shopify used to be laser-focused on the merchant (singular), specifically the entrepreneurial direct-to-consumer business, they are now focused on merchant s (plural), of all shapes and sizes. Oh, and those big enterprise merchants? They had no use for Shopify’s Fulfillment Network, reiterating the point that the cost wasn’t just money but actually a constriction of Shopify’s market opportunity. So no, to answer the analyst’s question, Shopify isn’t necessarily arming the rebels anymore; that theme is, of course, from the original Star Wars trilogy. What Shopify is doing now is more akin to a theme from the Disney trilogy: they’re an arms dealer, seeking scale on their software from any merchant who might ever have a need to buy — and they’re succeeding. This Update will be available as a podcast later today. To receive it in your podcast player, visit Stratechery . The Stratechery Update is intended for a single recipient, but occasional forwarding is totally fine! If you would like to order multiple subscriptions for your team with a group discount (minimum 5), please contact me directly. Thanks for being a subscriber, and have a great day! Listen to this update and other Stratechery Plus content in your podcast player: Stratechery | Sharp Tech | Dithering | Sharp China | Greatest Of All Talk Subscription Information Member: Omar Zoheri Email: stratecheryUSC@khamel.com Member since: April 23, 2022 Your subscription renews every year Renewal date: December 8, 2024 You are receiving this email because you are subscribed to Stratechery . Click here to view your account and manage your subscriptions. Click here to unsubscribe. © 2024 Stratechery LLC ,\n                                                        2093 Philadelphia Pike #9930, Claymont DE 19703",
      "table_data": {
        "rows": [
          [
            "View in browser Shopify Earnings, Software Self-Awareness, Rebels and the Arms Dealer Wednesday, November 13, 2024 Listen to this Update in your podcast player Good morning, On last week’s episode of Sharp China , Bill and Andrew reacted to Trump’s election and what it means for U.S.-China relations. On to the Update: Shopify Earnings From Bloomberg : Shopify Inc. soared after saying it will sustain rapid sales growth into the holiday shopping season, suggesting the Canadian e-commerce company’s strategy to lure larger businesses is paying off. Shopify said it expects percentage revenue growth for the current quarter ending in December to be in the mid to high twenties on a year-over-year basis. Analysts were looking for 23%. Shopify added 16 new enterprise clients in the third quarter, President Harley Finkelstein told investors on a Tuesday call. That helped boost revenue for the period by 26% to $2.16 billion, the company said in a statement Tuesday, beating the $2.12 billion average estimate of analysts surveyed by Bloomberg. In addition to attracting bigger customers, Shopify is benefiting from strength across Europe, more clients using its in-store payments tools and rapid growth in the business-to-business segment that’s attracting wholesale suppliers, Finkelstein said. “Shopify is not just for small businesses in North America,” he said. “We’re for every sized brand everywhere in the world.” Shopify is absolutely killing it. Finkelstein opened his prepared remarks with the numbers: As we say each quarter, Shopify is building for the long term. Our consistent results quarter after quarter confirm that our strategy is working incredibly well. Q3 was another amazing quarter across the board. GMV was up 24%, marking our fifth consecutive quarter where GMV growth was greater than 20%. Revenue was up 26%. Operating income more than doubled from last year. And free cash flow margin expanded to 19%. These are not just numbers. They reinforce that Shopify is an industry leader, delivering on both growth and margins, all while simultaneously creating and leaning into opportunities that bolster our growth. Finkelstein followed up with three things he wanted investors to remember: So, before we dive in, let me start by saying this. If you walk away from this call with anything, it should be these three things: One, entrepreneurship and commerce are growing, and Shopify is capturing an increasing share of this vast and expanding market. Two, Shopify is increasingly the go-to-platform of choice not just for entrepreneurship, but for all of commerce. We are well-positioned for extensive growth across different merchant segments, size, geographies, channels, and products. And three, as our merchants do better, Shopify does better. Our business model prioritizes merchant first, fueled by a high-velocity product innovation engine that makes the hard things easy and everything else possible. I would like to add a fourth thing; here is the chart of Shopify’s GMV over the last 10 years: The COVID boom is super obvious; what I think remains under-appreciated is the impact of ATT. I wrote in July 2022 after posting the above chart: You can clearly see the pandemic impact, but what is concerning is not simply that GMV growth returned to trend in late 2020, but, over the last two quarters, dropped below trend. That could be the pandemic hangover, it could be macroeconomic conditions, but it sure seems like the most obvious explanation is that it is the impact of ATT. It follows, then, that an under-appreciated reason for Shopify’s return to strength is Meta’s recovery from ATT: a lot of GMV is downstream from Meta ads in particular, and Meta’s return to growth is unsurprisingly correlated to Shopify’s return to growth as well. That noted, Shopify does deserve more credit than just riding Meta’s coattails; consistent growth rates above 20% is not a return to the pre-COVID trendline, but a clear acceleration to a new baseline, and here Finkelstein’s three things ring true, particularly point number two. Software Self-Awareness Finkelstein said in his closing statement: For those of you that have been following the Shopify story for quite some time, you know that we are a company that is laser-focused on our merchants. You’ve heard that we have a very long-term vision that we think could help them succeed. I think you will continue to see us seize opportunities and invest, as Jeff described, with discipline to further establish ourselves as the leader in commerce. And this has enabled us to deliver, as you can see from these results, some of the strongest results in the industry quarter after quarter. I also want to repeat, this is the best version of Shopify yet. We really like our size, our shape. We like how we’re operating. We really think it gives us the ability to grow the business and invest in the future. And so, I just wanted to finish with that point. And now for us, back to helping our merchants crush at this holiday season and well into the future. I don’t question Shopify’s laser-focus on merchants; what I would say, as someone who has been following the Shopify story for a long-time, is that it was precisely that focus that led Shopify astray a few years ago. To refresh your memory: That 2022 plummet in value wasn’t just the COVID overhang, and it wasn’t just ATT; it was also when Shopify decided to compete more directly with Amazon and get into the logistics business (beyond just being an asset-lite platform ). Finkelstein said on the February 2022 earnings call announcing the shift away from an asset-lite model: We are excited to update you today on what we’ve learned, how far we’ve come and especially on where we’re heading as we move out of the prototype phase and into the build phase. We are consolidating our network to larger facilities. We’ll operate more of them ourselves, and we’ll unify the warehouse management software that we’ve been building and testing over the past 18 months. We expect that these changes will enable us to deliver packages in 2 days or less to more than 90% of the U.S. population, while minimizing the inventory investment for SFN merchants. While Amy will go into more detail as to what our evolved vision looks like from a financial perspective, I can tell you, from a merchant’s perspective, Shopify Fulfillment can be life-changing for their businesses. We hear from merchants that fulfillment is only something you think about when it isn’t working well, and they are thrilled that they now never have to think about it. The stockouts and pre orders that took the shine off strong demand for the new releases, largely became, I think, in the past, with Shopify Fulfillment. And just recently, I heard from a merchant who tells me that he sleeps even better because Shopify Fulfillment just works. Comments like these fuel our ambition, and we’ll continue to explore opportunities to give merchants more visibility and control over their most important assets. That’s a lot of talk about merchants! It was also a disaster. Fast forward to May 2023 , and CEO Tobi Lütke announced layoffs and the end of Shopify’s logistics ambitions through the framework of “main quests” and “side quests”; logistics was the latter. Lütke claimed it was still worth it, but I’m not sure anyone agreed. Here’s the thing: logistics were and are a big challenge for merchants. It is a problem that needs to be solved. In this case, however, Shopify was too laser-focused on merchants; logistics was a situation where they needed to not just understand the problems being faced by their merchants, but also understand themselves and what problems they were actually capable of solving. Specifically, Shopify is a software company, and that puts one hard constraint on your business: you need to go horizontal, not vertical. Software requires huge amounts of R&D but it also scales infinitely; software businesses profit by maximizing leverage on their investments, which means serving more customers with the same capabilities. Logistics, though, means the physical world, which means variable costs and a limited addressable market; this limits the leverage you get from software, without decreasing the need for R&D. Rebels and the Arms Dealer That, then, takes me full circle to these results: what has shifted the curve for Shopify is not just shedding a logistics business that didn’t fit their nature, but in fact embracing their nature and working to expand their customer base. Note this (excellent) question and answer from yesterday’s earnings call: You guys have positioned Shopify as the rebels going up against the larger online marketplaces, but arguably the consolidation of e-commerce market share is occurring to a smaller number of platforms, including Shopify. And so, I wonder if your views of how the industry is evolving or changing, what that consolidation means for your merchant base, and ultimately, how that influences product plans for things like Shop App? Thank you. A couple of things are happening I think when it comes to larger brands and retailers. One is, all across the board, they’re looking for a unified commerce system. They’re not looking for standalone, single-channel products anymore. I’ve used this metaphor before of the browser and the browser tabs. And what we’re seeing is that these large companies, specifically complex ones that have high GMV, they want to collapse those tabs from eight to one. And this idea of having a modern future-proofed retail operating system that is unified across every channel like Shopify is very compelling. Secondly, historically, when it came to larger brands, our focus was really on Shopify Plus. We had sort of this one-size-fits-all for larger brands. But now we have an enterprise product, we have Shopify Plus, we have Commerce Components. And Commerce Components, in particular, is really compelling because it’ll — I mentioned this in my prepared remarks, but we’re now seeing brands that are calling us, and three weeks later, they now have Shop Pay installed on their checkout or brands, for example, like On Running, one of my favorite brands that has Shopify’s checkout as a Commerce Component that they’ve now taken. So, there are all these new sort of gateways into Shopify or on ramps to Shopify on the Enterprise side. There are two points here. First, Shopify has refocused its attention on delivering a solution to all aspect of a merchant’s software needs; this is what the company is capable of doing, and it increases both its value to merchants and also its attractiveness to larger companies. Secondly, Shopify has significantly increased both the segmentation of its products and their composability. Different capabilities are available at different price points and with different go-to-market approaches, but it all rests on a common R&D effort; similarly, companies can just use one or two of Shopify’s offerings, like the Shop Pay button, which both increases the leverage on that product and also provides a beachhead for selling more. In other words, while Shopify used to be laser-focused on the merchant (singular), specifically the entrepreneurial direct-to-consumer business, they are now focused on merchant s (plural), of all shapes and sizes. Oh, and those big enterprise merchants? They had no use for Shopify’s Fulfillment Network, reiterating the point that the cost wasn’t just money but actually a constriction of Shopify’s market opportunity. So no, to answer the analyst’s question, Shopify isn’t necessarily arming the rebels anymore; that theme is, of course, from the original Star Wars trilogy. What Shopify is doing now is more akin to a theme from the Disney trilogy: they’re an arms dealer, seeking scale on their software from any merchant who might ever have a need to buy — and they’re succeeding. This Update will be available as a podcast later today. To receive it in your podcast player, visit Stratechery . The Stratechery Update is intended for a single recipient, but occasional forwarding is totally fine! If you would like to order multiple subscriptions for your team with a group discount (minimum 5), please contact me directly. Thanks for being a subscriber, and have a great day! Listen to this update and other Stratechery Plus content in your podcast player: Stratechery",
            "Sharp Tech",
            "Dithering",
            "Sharp China",
            "Greatest Of All Talk Subscription Information Member: Omar Zoheri Email: stratecheryUSC@khamel.com Member since: April 23, 2022 Your subscription renews every year Renewal date: December 8, 2024 You are receiving this email because you are subscribed to Stratechery . Click here to view your account and manage your subscriptions. Click here to unsubscribe. © 2024 Stratechery LLC ,"
          ],
          [
            "2093 Philadelphia Pike #9930",
            "Claymont DE 19703"
          ]
        ],
        "columns": 5,
        "has_header": false
      }
    }
  ],
  "processing_timestamp": "2025-08-19T09:37:36.866284"
}